euroradscraper/__init__.py
euroradscraper/euroscraper.py
euroradscraper-1.0.dist-info/METADATA
euroradscraper-1.0.dist-info/WHEEL
euroradscraper-1.0.dist-info/top_level.txt
euroradscraper-1.0.dist-info/RECORD
